src/__init__.py
stellar_contract_sdk-0.1.0.dev0.dist-info/LICENSE
stellar_contract_sdk-0.1.0.dev0.dist-info/WHEEL
stellar_contract_sdk-0.1.0.dev0.dist-info/METADATA
stellar_contract_sdk-0.1.0.dev0.dist-info/RECORD
